setup.py
rattools/clustering.py
rattools/exploration.py
rattools/investing.py
rattools/sqlconnect.py
rattools.egg-info/PKG-INFO
rattools.egg-info/SOURCES.txt
rattools.egg-info/dependency_links.txt
rattools.egg-info/requires.txt
rattools.egg-info/top_level.txt