Metadata-Version: 1.0
Name: rattools
Version: 0.4.14
Summary: Este es un paquete de ejemplo
Home-page: UNKNOWN
Author: Ldog
Author-email: domgutluis@gmail.com
License: UNKNOWN
Platform: UNKNOWN
